<?xml version="1.0" encoding="utf-8"?>
<LanguageData>
  <!--The following translations were generated by https://www.deepl.com/-->
  <!-- EN: UN-Building -->
  <SadjuukUN-Building.label>联合国建筑</SadjuukUN-Building.label>
  <!-- EN: Available technologies from UN and UNSC colonization program -->
  <SadjuukUN-Building.description>联合国和联合国安理会殖民计划中的可用技术</SadjuukUN-Building.description>
  <!-- EN: UN-Furniture -->
  <SadjuukUN-Furniture.label>联合国家具</SadjuukUN-Furniture.label>
  <SadjuukUN-Furniture.description>联合国和联合国安理会殖民计划中的可用技术</SadjuukUN-Furniture.description>
  <!-- EN: UN-Industry -->
  <SadjuukUN-Industry.label>联合国工业</SadjuukUN-Industry.label>
  <SadjuukUN-Industry.description>联合国和联合国安理会殖民计划中的可用技术</SadjuukUN-Industry.description>
</LanguageData>
