<?xml version="1.0" encoding="utf-8"?>
<LanguageData>
  <!--The following translations were generated by https://www.deepl.com/-->
  <!-- EN: Wood Logs bed -->
  <SadjuukBedAA.label>Holzscheite Bett</SadjuukBedAA.label>
  <!-- EN: Beauty : 0\nComfort : 60%\nImmunity : +0%\nSurgery : -30%\nTending : +0%\nA simple wooden support to sleep on. It is found among the most primitive peoples and in the most infamous prisons. -->
  <SadjuukBedAA.description>Schönheit : 0
Komfort : 60%
Immunität : 0%
Chirurgie : -30%
Pflege : 0%
Eine einfache Holzunterlage zum Schlafen. Man findet sie bei den primitivsten Völkern und in den berüchtigtsten Gefängnissen.</SadjuukBedAA.description>
  <!-- EN: Double Logs bed -->
  <SadjuukBedroomAB.label>Double Logs Bett</SadjuukBedroomAB.label>
  <SadjuukBedroomAB.description>Schönheit : 0
Komfort : 60%
Immunität : 0%
Chirurgie : -30%
Pflege : 0%
Eine einfache Holzunterlage zum Schlafen. Man findet sie bei den primitivsten Völkern und in den berüchtigtsten Gefängnissen.</SadjuukBedroomAB.description>
  <!-- EN: Wooden Bed -->
  <SadjuukBedroomBA.label>Hölzernes Bett</SadjuukBedroomBA.label>
  <!-- EN: Beauty : 4\nComfort : 85%\nImmunity : +5%\nSurgery : +0%\nTending : +0%\nA comfortable bed made of wood giving a soft atmosphere to a room. -->
  <SadjuukBedroomBA.description>Schönheit : 4
Komfort : 85%
Immunität : 5%
Chirurgie : 0%
Pflegen : 0%
Ein bequemes Bett aus Holz, das dem Raum eine weiche Atmosphäre verleiht.</SadjuukBedroomBA.description>
  <!-- EN: Double Wooden Bed -->
  <SadjuukBedroomBB.label>Doppel-Holz-Bett</SadjuukBedroomBB.label>
  <SadjuukBedroomBB.description>Schönheit : 4
Komfort : 85%
Immunität : 5%
Chirurgie : 0%
Pflegen : 0%
Ein bequemes Bett aus Holz, das dem Raum eine weiche Atmosphäre verleiht.</SadjuukBedroomBB.description>
  <!-- EN: Steel Bed -->
  <SadjuukBedroomCA.label>Stahlbett</SadjuukBedroomCA.label>
  <!-- EN: Beauty : 2\nComfort : 75%\nImmunity : +8%\nSurgery : +0%\nTending : +0%\nA standard steel bed. Perfect for barracks, it also offers good hygiene properties. -->
  <SadjuukBedroomCA.description>Schönheit : 2
Komfort : 75%
Immunität : 8%
Chirurgie : 0%
Pflege : 0%
Ein Standard-Stahlbett. Ideal für Kasernen, bietet es auch gute Hygieneeigenschaften.</SadjuukBedroomCA.description>
  <!-- EN: Double Steel Bed -->
  <SadjuukBedroomCB.label>Doppeltes Stahlbett</SadjuukBedroomCB.label>
  <SadjuukBedroomCB.description>Schönheit : 2
Komfort : 75%
Immunität : 8%
Chirurgie : 0%
Pflege : 0%
Ein Standard-Stahlbett. Ideal für Kasernen, bietet es auch gute Hygieneeigenschaften.</SadjuukBedroomCB.description>
  <!-- EN: Wooden Chest -->
  <SadjuukBedroomUpgradeAA.label>Hölzerne Truhe</SadjuukBedroomUpgradeAA.label>
  <!-- EN: Beauty : 0\nComfort : +2%\nBedroom Upgrade : A personal wooden chest. Must be placed directly adjacent to the head of the bed. -->
  <SadjuukBedroomUpgradeAA.description>Schönheit : 0
Komfort : 2%
Schlafzimmer-Upgrade : Eine persönliche Holztruhe. Muss direkt neben dem Kopfende des Bettes platziert werden.</SadjuukBedroomUpgradeAA.description>
  <!-- EN: Wooden Storage -->
  <SadjuukBedroomUpgradeAB.label>Hölzerne Lagerung</SadjuukBedroomUpgradeAB.label>
  <!-- EN: Beauty : 0\nComfort : +2%\nBedroom Upgrade : Although made of simple wood, this piece of furniture at least allows you to store your personal belongings. -->
  <SadjuukBedroomUpgradeAB.description>Schönheit : 0
Komfort : 2%
Schlafzimmer-Upgrade : Obwohl es aus einfachem Holz besteht, bietet dieses Möbelstück zumindest die Möglichkeit, persönliche Gegenstände zu verstauen.</SadjuukBedroomUpgradeAB.description>
  <!-- EN: Small Log Table -->
  <SadjuukBedroomUpgradeAC.label>Kleine Log-Tabelle</SadjuukBedroomUpgradeAC.label>
  <!-- EN: Beauty : 0\nComfort : +2%\nBedroom Upgrade : A small primitive table. -->
  <SadjuukBedroomUpgradeAC.description>Schönheit : 0
Komfort : 2%
Schlafzimmer Upgrade : Ein kleiner primitiver Tisch.</SadjuukBedroomUpgradeAC.description>
  <!-- EN: Wood Logs Armchair -->
  <SadjuukBedroomUpgradeAF.label>Holzscheite Sessel</SadjuukBedroomUpgradeAF.label>
  <!-- EN: Beauty : 0\nComfort : +2%\nComfort : 70%\nBedroom Upgrade : A rigid wooden seat but still comfortable. -->
  <SadjuukBedroomUpgradeAF.description>Schönheit : 0
Komfort : 2%
Komfort : 70%
Schlafzimmer Upgrade : Ein harter Holzsitz, aber immer noch bequem.</SadjuukBedroomUpgradeAF.description>
  <!-- EN: Wooden Nightstand -->
  <SadjuukBedroomUpgradeBA.label>Hölzerner Nachttisch</SadjuukBedroomUpgradeBA.label>
  <!-- EN: Beauty : 4\nComfort : +2%\nBedroom Upgrade : A beautiful wooden Nightstand. Must be placed directly adjacent to the head of the bed. -->
  <SadjuukBedroomUpgradeBA.description>Schönheit : 4
Komfort : 2%
Schlafzimmer-Upgrade : Ein schöner hölzerner Nachttisch. Muss direkt neben dem Kopfende des Bettes platziert werden.</SadjuukBedroomUpgradeBA.description>
  <!-- EN: Wooden Wardrobe -->
  <SadjuukBedroomUpgradeBB.label>Hölzerne Garderobe</SadjuukBedroomUpgradeBB.label>
  <!-- EN: Beauty : 4\nComfort : +2%\nBedroom Upgrade : A large wooden wardrobe. -->
  <SadjuukBedroomUpgradeBB.description>Schönheit : 4
Komfort : 2%
Schlafzimmer Upgrade : Ein großer hölzerner Kleiderschrank.</SadjuukBedroomUpgradeBB.description>
  <!-- EN: Small Wooden Table -->
  <SadjuukBedroomUpgradeBC.label>Kleiner Holztisch</SadjuukBedroomUpgradeBC.label>
  <!-- EN: Beauty : 12\nComfort : +4%\nBedroom Upgrade : A finely decorated bedroom table. -->
  <SadjuukBedroomUpgradeBC.description>Schönheit : 12
Komfort : 4%
Schlafzimmer-Upgrade : Ein fein dekorierter Nachttisch.</SadjuukBedroomUpgradeBC.description>
  <!-- EN: Wooden Armchair -->
  <SadjuukBedroomUpgradeBF.label>Hölzerner Sessel</SadjuukBedroomUpgradeBF.label>
  <!-- EN: Beauty : 6\nComfort : +4%\nComfort : 80%\nBedroom Upgrade : A finely decorated seat. -->
  <SadjuukBedroomUpgradeBF.description>Schönheit : 6
Komfort : 4%
Komfort : 80%
Schlafzimmer-Upgrade : Ein fein dekorierter Sitz.</SadjuukBedroomUpgradeBF.description>
  <!-- EN: Steel Chest -->
  <SadjuukBedroomUpgradeCA.label>Stahltruhe</SadjuukBedroomUpgradeCA.label>
  <!-- EN: Beauty : 2\nComfort : +2%\nBedroom Upgrade : A personal steel chest, essential in the development of a civilian or military dormitory. Must be placed directly adjacent to the head of the bed. -->
  <SadjuukBedroomUpgradeCA.description>Schönheit : 2
Komfort : 2%
Schlafzimmer-Upgrade : Eine persönliche Stahltruhe, unverzichtbar für die Entwicklung eines zivilen oder militärischen Schlafsaals. Sie muss direkt neben dem Kopfende des Bettes platziert werden.</SadjuukBedroomUpgradeCA.description>
  <!-- EN: Steel Lockers -->
  <SadjuukBedroomUpgradeCB.label>Stahlschränke</SadjuukBedroomUpgradeCB.label>
  <!-- EN: Beauty : 2\nComfort : +2%\nBedroom Upgrade : Steel Lockers allowing a certain privacy. -->
  <SadjuukBedroomUpgradeCB.description>Schönheit : 2
Komfort : 2%
Schlafzimmer Upgrade : Stahlschränke, die eine gewisse Privatsphäre ermöglichen.</SadjuukBedroomUpgradeCB.description>
  <!-- EN: Small Steel Table -->
  <SadjuukBedroomUpgradeCC.label>Kleiner Stahltisch</SadjuukBedroomUpgradeCC.label>
  <!-- EN: Beauty : 2\nComfort : +2%\nBedroom Upgrade : A standard steel table. -->
  <SadjuukBedroomUpgradeCC.description>Schönheit : 2
Komfort : 2%
Schlafzimmer-Upgrade : Ein Standard-Stahltisch.</SadjuukBedroomUpgradeCC.description>
  <!-- EN: Small Glass Table -->
  <SadjuukBedroomUpgradeCD.label>Kleiner Glastisch</SadjuukBedroomUpgradeCD.label>
  <!-- EN: Beauty : 6\nComfort : +2%\nBedroom Upgrade : A small glass table making nearby beds a little bit more comfortable. -->
  <SadjuukBedroomUpgradeCD.description>Schönheit : 6
Komfort : 2%
Schlafzimmer-Upgrade : Ein kleiner Glastisch, der die Betten in der Nähe ein wenig bequemer macht.</SadjuukBedroomUpgradeCD.description>
  <!-- EN: Office Chair -->
  <SadjuukBedroomUpgradeCF.label>Bürostuhl</SadjuukBedroomUpgradeCF.label>
  <!-- EN: Beauty : 2\nComfort : +2%\nComfort : 75%\nBedroom Upgrade : A complex but comfortable manufacturing armchair. -->
  <SadjuukBedroomUpgradeCF.description>Schönheit : 2
Komfort : 2%
Komfort : 75%
Schlafzimmer-Upgrade : Ein komplexer, aber bequemer Fertigungssessel.</SadjuukBedroomUpgradeCF.description>
</LanguageData>
